quickdiff-0.1.5.dist-info/METADATA
quickdiff-0.1.5.dist-info/WHEEL
quickdiff/__init__.py
quickdiff/py.typed
quickdiff/quickdiff.cpython-311-darwin.so
quickdiff-0.1.5.dist-info/RECORD
