Metadata-Version: 2.1
Name: quickdiff
Version: 0.1.5
Classifier: Programming Language :: Rust
Classifier: Programming Language :: Python :: Implementation :: CPython
Classifier: Programming Language :: Python :: Implementation :: PyPy
Requires-Python: >=3.7
Project-URL: repository, https://github.com/CallumJHays/quickdiff
